MANIFEST.in
README.rst
setup.cfg
setup.py
versioneer.py
ciscosparkapi/__init__.py
ciscosparkapi/_version.py
ciscosparkapi/exceptions.py
ciscosparkapi/generator_containers.py
ciscosparkapi/response_codes.py
ciscosparkapi/restsession.py
ciscosparkapi/utils.py
ciscosparkapi.egg-info/PKG-INFO
ciscosparkapi.egg-info/SOURCES.txt
ciscosparkapi.egg-info/dependency_links.txt
ciscosparkapi.egg-info/requires.txt
ciscosparkapi.egg-info/top_level.txt
ciscosparkapi/api/__init__.py
ciscosparkapi/api/access_tokens.py
ciscosparkapi/api/events.py
ciscosparkapi/api/licenses.py
ciscosparkapi/api/memberships.py
ciscosparkapi/api/messages.py
ciscosparkapi/api/organizations.py
ciscosparkapi/api/people.py
ciscosparkapi/api/roles.py
ciscosparkapi/api/rooms.py
ciscosparkapi/api/team_memberships.py
ciscosparkapi/api/teams.py
ciscosparkapi/api/webhooks.py
ciscosparkapi/models/__init__.py
ciscosparkapi/models/access_token.py
ciscosparkapi/models/event.py
ciscosparkapi/models/license.py
ciscosparkapi/models/membership.py
ciscosparkapi/models/message.py
ciscosparkapi/models/organization.py
ciscosparkapi/models/person.py
ciscosparkapi/models/role.py
ciscosparkapi/models/room.py
ciscosparkapi/models/simple.py
ciscosparkapi/models/sparkdata.py
ciscosparkapi/models/team.py
ciscosparkapi/models/team_membership.py
ciscosparkapi/models/webhook.py
ciscosparkapi/models/webhook_event.py