Metadata-Version: 1.1
Name: ciscosparkapi
Version: 0.10.1
Summary: Simple, lightweight, scalable Python API wrapper for the Cisco Spark APIs
Home-page: https://github.com/CiscoDevNet/ciscosparkapi
Author: Chris Lunsford
Author-email: chrlunsf@cisco.com
License: MIT; Copyright (c) 2016-2018 Cisco and/or its affiliates.
Download-URL: https://pypi.python.org/pypi/ciscosparkapi
Keywords: cisco spark api enterprise messaging
Platform: UNKNOWN
Classifier: Development Status :: 4 - Beta
Classifier: Intended Audience :: Developers
Classifier: Intended Audience :: System Administrators
Classifier: Intended Audience :: Telecommunications Industry
Classifier: Intended Audience :: Education
Classifier: Natural Language :: English
Classifier: License :: OSI Approved :: MIT License
Classifier: Programming Language :: Python :: 2
Classifier: Programming Language :: Python :: 2.7
Classifier: Programming Language :: Python :: 3
Classifier: Programming Language :: Python :: 3.5
Classifier: Programming Language :: Python :: 3.6
Classifier: Topic :: Communications
Classifier: Topic :: Communications :: Chat
